py2img/__init__.py
py2img/decoder.py
py2img/encoder.py
py2img/settings.py
py2img-0.1.dist-info/METADATA
py2img-0.1.dist-info/WHEEL
py2img-0.1.dist-info/top_level.txt
py2img-0.1.dist-info/RECORD
